Metadata-Version: 2.1
Name: vulcan-builder
Version: 0.2.3
Summary: Lightweight Python Build Tool.
Home-page: https://code.exrny.com/opensource/vulcan-builder/
Author: Peter Salnikov
Author-email: opensource@exrny.com
License: MIT License
Keywords: devops,build tool
Classifier: Development Status :: 4 - Beta
Classifier: Environment :: Console
Classifier: Intended Audience :: System Administrators
Classifier: Intended Audience :: Developers
Classifier: License :: OSI Approved :: MIT License
Classifier: Programming Language :: Python :: 2
Classifier: Programming Language :: Python :: 3
Classifier: Topic :: Software Development :: Build Tools
License-File: LICENSE.txt
